arcane/storage.py
arcane_storage-0.4.8.dist-info/METADATA
arcane_storage-0.4.8.dist-info/WHEEL
arcane_storage-0.4.8.dist-info/RECORD
