Metadata-Version: 2.4
Name: arcane-storage
Version: 0.4.8
Summary: 
Author: Arcane
Author-email: product@wearcane.com
Requires-Python: >=3.7,<4.0
Classifier: Programming Language :: Python :: 3
Classifier: Programming Language :: Python :: 3.7
Classifier: Programming Language :: Python :: 3.8
Classifier: Programming Language :: Python :: 3.9
Classifier: Programming Language :: Python :: 3.10
Classifier: Programming Language :: Python :: 3.11
Classifier: Programming Language :: Python :: 3.12
Classifier: Programming Language :: Python :: 3.13
Classifier: Programming Language :: Python :: 3.14
Requires-Dist: arcane-core (>=1.6,<2.0)
Requires-Dist: backoff (>=1.10.0)
Requires-Dist: google-cloud-storage (>=2.7,<3.0)
